pyroll/work_roll_elastic_deformation/__init__.py
pyroll/work_roll_elastic_deformation/disk_element.py
pyroll/work_roll_elastic_deformation/matix_method.py
pyroll/work_roll_elastic_deformation/reporter_impls.py
pyroll/work_roll_elastic_deformation/roll_body.py
pyroll/work_roll_elastic_deformation/roll_hookimpls.py
pyroll/work_roll_elastic_deformation/roll_hookspecs.py
pyroll/work_roll_elastic_deformation/rollpass_roll_hookimpls.py
pyroll/work_roll_elastic_deformation/rollpass_roll_hookspecs.py
pyroll_work_roll_elastic_deformation-1.0.0.dist-info/LICENSE
pyroll_work_roll_elastic_deformation-1.0.0.dist-info/WHEEL
pyroll_work_roll_elastic_deformation-1.0.0.dist-info/METADATA
pyroll_work_roll_elastic_deformation-1.0.0.dist-info/RECORD
